corens/__init__.py
corens/arrghs.py
corens/cfg.py
corens/cfg_grammar.py
corens/console.py
corens/daemon.py
corens/env.py
corens/gevt.py
corens/help.py
corens/hylang.py
corens/init.py
corens/log.py
corens/mod.py
corens/ns.py
corens/shell.py
corens/sig.py
corens/tpl.py
corens/txt.py
corens/version.py
corens/vns.py
corens/bund/__init__.py
corens/bund/vm.py
corens/stdlib/__init__.py
corens/stdlib/nsBase.py
corens/stdlib/nsDaemon.py
corens/stdlib/nsDisk.py
corens/stdlib/nsGevent.py
corens/stdlib/nsNetwork.py
corens/stdlib/nsOS.py
corens/stdlib/nsRandom.py
corens/stdlib/nsTime.py
corens/stdlib/nsUUID.py
corens/stdlib/nsVNS.py
corens/testlib/__init__.py
corens/testlib/testmain.py
corens-0.0.7.dist-info/LICENSE
corens-0.0.7.dist-info/METADATA
corens-0.0.7.dist-info/WHEEL
corens-0.0.7.dist-info/top_level.txt
corens-0.0.7.dist-info/RECORD
